netbox_toolkit_plugin/__init__.py
netbox_toolkit_plugin/admin.py
netbox_toolkit_plugin/exceptions.py
netbox_toolkit_plugin/filtersets.py
netbox_toolkit_plugin/forms.py
netbox_toolkit_plugin/models.py
netbox_toolkit_plugin/navigation.py
netbox_toolkit_plugin/search.py
netbox_toolkit_plugin/settings.py
netbox_toolkit_plugin/tables.py
netbox_toolkit_plugin/urls.py
netbox_toolkit_plugin/api/__init__.py
netbox_toolkit_plugin/api/mixins.py
netbox_toolkit_plugin/api/schemas.py
netbox_toolkit_plugin/api/serializers.py
netbox_toolkit_plugin/api/urls.py
netbox_toolkit_plugin/api/views/__init__.py
netbox_toolkit_plugin/api/views/command_logs.py
netbox_toolkit_plugin/api/views/commands.py
netbox_toolkit_plugin/connectors/__init__.py
netbox_toolkit_plugin/connectors/base.py
netbox_toolkit_plugin/connectors/factory.py
netbox_toolkit_plugin/connectors/netmiko_connector.py
netbox_toolkit_plugin/connectors/scrapli_connector.py
netbox_toolkit_plugin/migrations/0001_initial.py
netbox_toolkit_plugin/migrations/0002_alter_command_options_alter_command_unique_together_and_more.py
netbox_toolkit_plugin/migrations/0003_permission_system_update.py
netbox_toolkit_plugin/migrations/0004_remove_django_permissions.py
netbox_toolkit_plugin/migrations/0005_alter_command_options_and_more.py
netbox_toolkit_plugin/migrations/0006_commandlog_parsed_data_commandlog_parsing_success_and_more.py
netbox_toolkit_plugin/migrations/0007_alter_commandlog_parsing_template.py
netbox_toolkit_plugin/migrations/0008_remove_parsed_data_storage.py
netbox_toolkit_plugin/migrations/0009_convert_platform_to_many_to_many.py
netbox_toolkit_plugin/migrations/0010_add_command_variables.py
netbox_toolkit_plugin/migrations/0011_remove_orphaned_variables_column.py
netbox_toolkit_plugin/migrations/0012_alter_command_unique_together_devicecredentialset.py
netbox_toolkit_plugin/migrations/0013_alter_devicecredentialset_access_token.py
netbox_toolkit_plugin/migrations/0014_add_encrypted_token_field.py
netbox_toolkit_plugin-0.1.5.dist-info/licenses/LICENSE
netbox_toolkit_plugin-0.1.5.dist-info/METADATA
netbox_toolkit_plugin-0.1.5.dist-info/WHEEL
netbox_toolkit_plugin-0.1.5.dist-info/entry_points.txt
netbox_toolkit_plugin-0.1.5.dist-info/top_level.txt
netbox_toolkit_plugin-0.1.5.dist-info/RECORD
