Metadata-Version: 2.4
Name: netbox-toolkit-plugin
Version: 0.1.5
Summary: NetBox plugin for running pre-defined commands on network devices
Author: Andy Norwood
Classifier: Development Status :: 3 - Alpha
Classifier: Intended Audience :: System Administrators
Classifier: Natural Language :: English
Classifier: Programming Language :: Python :: 3 :: Only
Classifier: Programming Language :: Python :: 3.10
Classifier: Programming Language :: Python :: 3.11
Classifier: Programming Language :: Python :: 3.12
Requires-Python: >=3.10.0
License-File: LICENSE
Requires-Dist: scrapli>=2023.1.30
Requires-Dist: scrapli-netconf>=2023.1.30
Requires-Dist: scrapli-community>=2023.1.30
Requires-Dist: netmiko>=4.0.0
Requires-Dist: cryptography>=41.0.0
Requires-Dist: argon2-cffi>=23.1.0
Dynamic: license-file
